{"pulls_url":"https:\/\/api.github.com\/repos\/4d-for-ios\/form-list-SquareProfile\/pulls{\/number}","default_branch":"master","labels_url":"https:\/\/api.github.com\/repos\/4d-for-ios\/form-list-SquareProfile\/labels{\/name}","watchers":0,"keys_url":"https:\/\/api.github.com\/repos\/4d-for-ios\/form-list-SquareProfile\/keys{\/key_id}","network_count":0,"tags_url":"https:\/\/api.github.com\/repos\/4d-for-ios\/form-list-SquareProfile\/tags","stargazers_url":"https:\/\/api.github.com\/repos\/4d-for-ios\/form-list-SquareProfile\/stargazers","url":"https:\/\/api.github.com\/repos\/4d-for-ios\/form-list-SquareProfile","assignees_url":"https:\/\/api.github.com\/repos\/4d-for-ios\/form-list-SquareProfile\/assignees{\/user}","description":"4D for iOS List Form template","subscribers_url":"https:\/\/api.github.com\/repos\/4d-for-ios\/form-list-SquareProfile\/subscribers","id":218803512,"branches_url":"https:\/\/api.github.com\/repos\/4d-for-ios\/form-list-SquareProfile\/branches{\/branch}","issue_events_url":"https:\/\/api.github.com\/repos\/4d-for-ios\/form-list-SquareProfile\/issues\/events{\/number}","html_url":"https:\/\/github.com\/4d-for-ios\/form-list-SquareProfile","clone_url":"https:\/\/github.com\/4d-for-ios\/form-list-SquareProfile.git","subscribers_count":2,"license":{"spdx_id":"NOASSERTION","key":"other","node_id":"MDc6TGljZW5zZTA=","name":"Other","url":null},"issues_url":"https:\/\/api.github.com\/repos\/4d-for-ios\/form-list-SquareProfile\/issues{\/number}","releases_url":"https:\/\/api.github.com\/repos\/4d-for-ios\/form-list-SquareProfile\/releases{\/id}","stargazers_count":0,"ssh_url":"git@github.com:4d-for-ios\/form-list-SquareProfile.git","node_id":"MDEwOlJlcG9zaXRvcnkyMTg4MDM1MTI=","has_downloads":true,"compare_url":"https:\/\/api.github.com\/repos\/4d-for-ios\/form-list-SquareProfile\/compare\/{base}...{head}","deployments_url":"https:\/\/api.github.com\/repos\/4d-for-ios\/form-list-SquareProfile\/deployments","downloads_url":"https:\/\/api.github.com\/repos\/4d-for-ios\/form-list-SquareProfile\/downloads","mirror_url":null,"watchers_count":0,"notifications_url":"https:\/\/api.github.com\/repos\/4d-for-ios\/form-list-SquareProfile\/notifications{?since,all,participating}","homepage":"","open_issues_count":0,"git_commits_url":"https:\/\/api.github.com\/repos\/4d-for-ios\/form-list-SquareProfile\/git\/commits{\/sha}","temp_clone_token":"","hooks_url":"https:\/\/api.github.com\/repos\/4d-for-ios\/form-list-SquareProfile\/hooks","fork":false,"open_issues":0,"has_projects":true,"release":{"zipball_url":"https:\/\/api.github.com\/repos\/4d-for-ios\/form-list-SquareProfile\/zipball\/0.0.1","draft":false,"target_commitish":"master","id":21737576,"created_at":"2019-11-25T09:46:47Z","author":{"gravatar_id":"","repos_url":"https:\/\/api.github.com\/users\/phimage\/repos","login":"phimage","avatar_url":"https:\/\/avatars.githubusercontent.com\/u\/8875768?v=4","events_url":"https:\/\/api.github.com\/users\/phimage\/events{\/privacy}","url":"https:\/\/api.github.com\/users\/phimage","gists_url":"https:\/\/api.github.com\/users\/phimage\/gists{\/gist_id}","site_admin":false,"type":"User","following_url":"https:\/\/api.github.com\/users\/phimage\/following{\/other_user}","organizations_url":"https:\/\/api.github.com\/users\/phimage\/orgs","received_events_url":"https:\/\/api.github.com\/users\/phimage\/received_events","html_url":"https:\/\/github.com\/phimage","starred_url":"https:\/\/api.github.com\/users\/phimage\/starred{\/owner}{\/repo}","subscriptions_url":"https:\/\/api.github.com\/users\/phimage\/subscriptions","node_id":"MDQ6VXNlcjg4NzU3Njg=","id":8875768,"followers_url":"https:\/\/api.github.com\/users\/phimage\/followers"},"tag_name":"0.0.1","prerelease":false,"name":null,"html_url":"https:\/\/github.com\/4d-for-ios\/form-list-SquareProfile\/releases\/tag\/0.0.1","assets":[{"browser_download_url":"https:\/\/github.com\/4d-for-ios\/form-list-SquareProfile\/releases\/download\/0.0.1\/form-list-SquareProfile.zip","updated_at":"2019-11-25T15:48:06Z","label":"","url":"https:\/\/api.github.com\/repos\/4d-for-ios\/form-list-SquareProfile\/releases\/assets\/16386629","state":"uploaded","name":"form-list-SquareProfile.zip","created_at":"2019-11-25T15:48:06Z","node_id":"MDEyOlJlbGVhc2VBc3NldDE2Mzg2NjI5","id":16386629,"content_type":"application\/zip","size":2035800,"download_count":36,"uploader":{"site_admin":false,"avatar_url":"https:\/\/avatars.githubusercontent.com\/in\/15368?v=4","organizations_url":"https:\/\/api.github.com\/users\/github-actions%5Bbot%5D\/orgs","url":"https:\/\/api.github.com\/users\/github-actions%5Bbot%5D","subscriptions_url":"https:\/\/api.github.com\/users\/github-actions%5Bbot%5D\/subscriptions","gravatar_id":"","html_url":"https:\/\/github.com\/apps\/github-actions","starred_url":"https:\/\/api.github.com\/users\/github-actions%5Bbot%5D\/starred{\/owner}{\/repo}","id":41898282,"type":"Bot","login":"github-actions[bot]","following_url":"https:\/\/api.github.com\/users\/github-actions%5Bbot%5D\/following{\/other_user}","received_events_url":"https:\/\/api.github.com\/users\/github-actions%5Bbot%5D\/received_events","gists_url":"https:\/\/api.github.com\/users\/github-actions%5Bbot%5D\/gists{\/gist_id}","repos_url":"https:\/\/api.github.com\/users\/github-actions%5Bbot%5D\/repos","followers_url":"https:\/\/api.github.com\/users\/github-actions%5Bbot%5D\/followers","node_id":"MDM6Qm90NDE4OTgyODI=","events_url":"https:\/\/api.github.com\/users\/github-actions%5Bbot%5D\/events{\/privacy}"}}],"node_id":"MDc6UmVsZWFzZTIxNzM3NTc2","upload_url":"https:\/\/uploads.github.com\/repos\/4d-for-ios\/form-list-SquareProfile\/releases\/21737576\/assets{?name,label}","assets_url":"https:\/\/api.github.com\/repos\/4d-for-ios\/form-list-SquareProfile\/releases\/21737576\/assets","tarball_url":"https:\/\/api.github.com\/repos\/4d-for-ios\/form-list-SquareProfile\/tarball\/0.0.1","url":"https:\/\/api.github.com\/repos\/4d-for-ios\/form-list-SquareProfile\/releases\/21737576","body":"🚀 Initial release","published_at":"2019-11-25T15:43:29Z"},"disabled":false,"archive_url":"https:\/\/api.github.com\/repos\/4d-for-ios\/form-list-SquareProfile\/{archive_format}{\/ref}","archived":false,"comments_url":"https:\/\/api.github.com\/repos\/4d-for-ios\/form-list-SquareProfile\/comments{\/number}","contents_url":"https:\/\/api.github.com\/repos\/4d-for-ios\/form-list-SquareProfile\/contents\/{+path}","blobs_url":"https:\/\/api.github.com\/repos\/4d-for-ios\/form-list-SquareProfile\/git\/blobs{\/sha}","created_at":"2019-10-31T15:54:06Z","forks_count":0,"size":1998,"collaborators_url":"https:\/\/api.github.com\/repos\/4d-for-ios\/form-list-SquareProfile\/collaborators{\/collaborator}","name":"form-list-SquareProfile","git_refs_url":"https:\/\/api.github.com\/repos\/4d-for-ios\/form-list-SquareProfile\/git\/refs{\/sha}","commits_url":"https:\/\/api.github.com\/repos\/4d-for-ios\/form-list-SquareProfile\/commits{\/sha}","owner":{"followers_url":"https:\/\/api.github.com\/users\/4d-for-ios\/followers","following_url":"https:\/\/api.github.com\/users\/4d-for-ios\/following{\/other_user}","starred_url":"https:\/\/api.github.com\/users\/4d-for-ios\/starred{\/owner}{\/repo}","organizations_url":"https:\/\/api.github.com\/users\/4d-for-ios\/orgs","received_events_url":"https:\/\/api.github.com\/users\/4d-for-ios\/received_events","gravatar_id":"","url":"https:\/\/api.github.com\/users\/4d-for-ios","node_id":"MDEyOk9yZ2FuaXphdGlvbjU3NDgzNzgx","repos_url":"https:\/\/api.github.com\/users\/4d-for-ios\/repos","login":"4d-for-ios","avatar_url":"https:\/\/avatars.githubusercontent.com\/u\/57483781?v=4","site_admin":false,"html_url":"https:\/\/github.com\/4d-for-ios","subscriptions_url":"https:\/\/api.github.com\/users\/4d-for-ios\/subscriptions","id":57483781,"events_url":"https:\/\/api.github.com\/users\/4d-for-ios\/events{\/privacy}","type":"Organization","gists_url":"https:\/\/api.github.com\/users\/4d-for-ios\/gists{\/gist_id}"},"teams_url":"https:\/\/api.github.com\/repos\/4d-for-ios\/form-list-SquareProfile\/teams","forks_url":"https:\/\/api.github.com\/repos\/4d-for-ios\/form-list-SquareProfile\/forks","git_tags_url":"https:\/\/api.github.com\/repos\/4d-for-ios\/form-list-SquareProfile\/git\/tags{\/sha}","has_issues":true,"events_url":"https:\/\/api.github.com\/repos\/4d-for-ios\/form-list-SquareProfile\/events","subscription_url":"https:\/\/api.github.com\/repos\/4d-for-ios\/form-list-SquareProfile\/subscription","forks":0,"trees_url":"https:\/\/api.github.com\/repos\/4d-for-ios\/form-list-SquareProfile\/git\/trees{\/sha}","issue_comment_url":"https:\/\/api.github.com\/repos\/4d-for-ios\/form-list-SquareProfile\/issues\/comments{\/number}","languages_url":"https:\/\/api.github.com\/repos\/4d-for-ios\/form-list-SquareProfile\/languages","statuses_url":"https:\/\/api.github.com\/repos\/4d-for-ios\/form-list-SquareProfile\/statuses\/{sha}","merges_url":"https:\/\/api.github.com\/repos\/4d-for-ios\/form-list-SquareProfile\/merges","organization":{"followers_url":"https:\/\/api.github.com\/users\/4d-for-ios\/followers","following_url":"https:\/\/api.github.com\/users\/4d-for-ios\/following{\/other_user}","starred_url":"https:\/\/api.github.com\/users\/4d-for-ios\/starred{\/owner}{\/repo}","organizations_url":"https:\/\/api.github.com\/users\/4d-for-ios\/orgs","received_events_url":"https:\/\/api.github.com\/users\/4d-for-ios\/received_events","gravatar_id":"","url":"https:\/\/api.github.com\/users\/4d-for-ios","node_id":"MDEyOk9yZ2FuaXphdGlvbjU3NDgzNzgx","repos_url":"https:\/\/api.github.com\/users\/4d-for-ios\/repos","login":"4d-for-ios","avatar_url":"https:\/\/avatars.githubusercontent.com\/u\/57483781?v=4","site_admin":false,"html_url":"https:\/\/github.com\/4d-for-ios","subscriptions_url":"https:\/\/api.github.com\/users\/4d-for-ios\/subscriptions","id":57483781,"events_url":"https:\/\/api.github.com\/users\/4d-for-ios\/events{\/privacy}","type":"Organization","gists_url":"https:\/\/api.github.com\/users\/4d-for-ios\/gists{\/gist_id}"},"svn_url":"https:\/\/github.com\/4d-for-ios\/form-list-SquareProfile","private":false,"pushed_at":"2020-01-17T09:06:45Z","git_url":"git:\/\/github.com\/4d-for-ios\/form-list-SquareProfile.git","updated_at":"2020-01-17T09:06:47Z","milestones_url":"https:\/\/api.github.com\/repos\/4d-for-ios\/form-list-SquareProfile\/milestones{\/number}","has_pages":false,"permissions":{"pull":false,"admin":false,"push":false},"full_name":"4d-for-ios\/form-list-SquareProfile","visibility":"public","contributors_url":"https:\/\/api.github.com\/repos\/4d-for-ios\/form-list-SquareProfile\/contributors","has_wiki":true,"language":"Swift"}