{"homepage":"","network_count":0,"has_pages":false,"watchers":0,"comments_url":"https:\/\/api.github.com\/repos\/4d-for-ios\/form-list-SquareProfile\/comments{\/number}","has_wiki":true,"git_url":"git:\/\/github.com\/4d-for-ios\/form-list-SquareProfile.git","svn_url":"https:\/\/github.com\/4d-for-ios\/form-list-SquareProfile","subscribers_url":"https:\/\/api.github.com\/repos\/4d-for-ios\/form-list-SquareProfile\/subscribers","languages_url":"https:\/\/api.github.com\/repos\/4d-for-ios\/form-list-SquareProfile\/languages","issue_comment_url":"https:\/\/api.github.com\/repos\/4d-for-ios\/form-list-SquareProfile\/issues\/comments{\/number}","mirror_url":null,"downloads_url":"https:\/\/api.github.com\/repos\/4d-for-ios\/form-list-SquareProfile\/downloads","html_url":"https:\/\/github.com\/4d-for-ios\/form-list-SquareProfile","collaborators_url":"https:\/\/api.github.com\/repos\/4d-for-ios\/form-list-SquareProfile\/collaborators{\/collaborator}","branches_url":"https:\/\/api.github.com\/repos\/4d-for-ios\/form-list-SquareProfile\/branches{\/branch}","fork":false,"hooks_url":"https:\/\/api.github.com\/repos\/4d-for-ios\/form-list-SquareProfile\/hooks","stargazers_url":"https:\/\/api.github.com\/repos\/4d-for-ios\/form-list-SquareProfile\/stargazers","issue_events_url":"https:\/\/api.github.com\/repos\/4d-for-ios\/form-list-SquareProfile\/issues\/events{\/number}","has_downloads":true,"name":"form-list-SquareProfile","keys_url":"https:\/\/api.github.com\/repos\/4d-for-ios\/form-list-SquareProfile\/keys{\/key_id}","subscribers_count":2,"release":{"tag_name":"0.0.1","published_at":"2019-11-25T15:43:29Z","id":21737576,"assets":[{"node_id":"MDEyOlJlbGVhc2VBc3NldDE2Mzg2NjI5","download_count":36,"uploader":{"login":"github-actions[bot]","organizations_url":"https:\/\/api.github.com\/users\/github-actions%5Bbot%5D\/orgs","received_events_url":"https:\/\/api.github.com\/users\/github-actions%5Bbot%5D\/received_events","events_url":"https:\/\/api.github.com\/users\/github-actions%5Bbot%5D\/events{\/privacy}","followers_url":"https:\/\/api.github.com\/users\/github-actions%5Bbot%5D\/followers","following_url":"https:\/\/api.github.com\/users\/github-actions%5Bbot%5D\/following{\/other_user}","url":"https:\/\/api.github.com\/users\/github-actions%5Bbot%5D","subscriptions_url":"https:\/\/api.github.com\/users\/github-actions%5Bbot%5D\/subscriptions","starred_url":"https:\/\/api.github.com\/users\/github-actions%5Bbot%5D\/starred{\/owner}{\/repo}","html_url":"https:\/\/github.com\/apps\/github-actions","repos_url":"https:\/\/api.github.com\/users\/github-actions%5Bbot%5D\/repos","gists_url":"https:\/\/api.github.com\/users\/github-actions%5Bbot%5D\/gists{\/gist_id}","site_admin":false,"gravatar_id":"","node_id":"MDM6Qm90NDE4OTgyODI=","id":41898282,"type":"Bot","avatar_url":"https:\/\/avatars.githubusercontent.com\/in\/15368?v=4"},"label":"","state":"uploaded","content_type":"application\/zip","updated_at":"2019-11-25T15:48:06Z","url":"https:\/\/api.github.com\/repos\/4d-for-ios\/form-list-SquareProfile\/releases\/assets\/16386629","created_at":"2019-11-25T15:48:06Z","browser_download_url":"https:\/\/github.com\/4d-for-ios\/form-list-SquareProfile\/releases\/download\/0.0.1\/form-list-SquareProfile.zip","size":2035800,"id":16386629,"name":"form-list-SquareProfile.zip"}],"prerelease":false,"html_url":"https:\/\/github.com\/4d-for-ios\/form-list-SquareProfile\/releases\/tag\/0.0.1","zipball_url":"https:\/\/api.github.com\/repos\/4d-for-ios\/form-list-SquareProfile\/zipball\/0.0.1","target_commitish":"master","name":null,"assets_url":"https:\/\/api.github.com\/repos\/4d-for-ios\/form-list-SquareProfile\/releases\/21737576\/assets","upload_url":"https:\/\/uploads.github.com\/repos\/4d-for-ios\/form-list-SquareProfile\/releases\/21737576\/assets{?name,label}","author":{"site_admin":false,"node_id":"MDQ6VXNlcjg4NzU3Njg=","gists_url":"https:\/\/api.github.com\/users\/phimage\/gists{\/gist_id}","html_url":"https:\/\/github.com\/phimage","login":"phimage","organizations_url":"https:\/\/api.github.com\/users\/phimage\/orgs","received_events_url":"https:\/\/api.github.com\/users\/phimage\/received_events","subscriptions_url":"https:\/\/api.github.com\/users\/phimage\/subscriptions","url":"https:\/\/api.github.com\/users\/phimage","following_url":"https:\/\/api.github.com\/users\/phimage\/following{\/other_user}","gravatar_id":"","avatar_url":"https:\/\/avatars.githubusercontent.com\/u\/8875768?v=4","events_url":"https:\/\/api.github.com\/users\/phimage\/events{\/privacy}","starred_url":"https:\/\/api.github.com\/users\/phimage\/starred{\/owner}{\/repo}","type":"User","repos_url":"https:\/\/api.github.com\/users\/phimage\/repos","id":8875768,"followers_url":"https:\/\/api.github.com\/users\/phimage\/followers"},"body":"🚀 Initial release","tarball_url":"https:\/\/api.github.com\/repos\/4d-for-ios\/form-list-SquareProfile\/tarball\/0.0.1","node_id":"MDc6UmVsZWFzZTIxNzM3NTc2","url":"https:\/\/api.github.com\/repos\/4d-for-ios\/form-list-SquareProfile\/releases\/21737576","created_at":"2019-11-25T09:46:47Z","draft":false},"temp_clone_token":"","releases_url":"https:\/\/api.github.com\/repos\/4d-for-ios\/form-list-SquareProfile\/releases{\/id}","visibility":"public","teams_url":"https:\/\/api.github.com\/repos\/4d-for-ios\/form-list-SquareProfile\/teams","git_tags_url":"https:\/\/api.github.com\/repos\/4d-for-ios\/form-list-SquareProfile\/git\/tags{\/sha}","has_issues":true,"open_issues":0,"notifications_url":"https:\/\/api.github.com\/repos\/4d-for-ios\/form-list-SquareProfile\/notifications{?since,all,participating}","git_refs_url":"https:\/\/api.github.com\/repos\/4d-for-ios\/form-list-SquareProfile\/git\/refs{\/sha}","permissions":{"pull":false,"admin":false,"push":false},"git_commits_url":"https:\/\/api.github.com\/repos\/4d-for-ios\/form-list-SquareProfile\/git\/commits{\/sha}","private":false,"id":218803512,"ssh_url":"git@github.com:4d-for-ios\/form-list-SquareProfile.git","tags_url":"https:\/\/api.github.com\/repos\/4d-for-ios\/form-list-SquareProfile\/tags","updated_at":"2020-01-17T09:06:47Z","url":"https:\/\/api.github.com\/repos\/4d-for-ios\/form-list-SquareProfile","blobs_url":"https:\/\/api.github.com\/repos\/4d-for-ios\/form-list-SquareProfile\/git\/blobs{\/sha}","contributors_url":"https:\/\/api.github.com\/repos\/4d-for-ios\/form-list-SquareProfile\/contributors","events_url":"https:\/\/api.github.com\/repos\/4d-for-ios\/form-list-SquareProfile\/events","has_projects":true,"subscription_url":"https:\/\/api.github.com\/repos\/4d-for-ios\/form-list-SquareProfile\/subscription","trees_url":"https:\/\/api.github.com\/repos\/4d-for-ios\/form-list-SquareProfile\/git\/trees{\/sha}","pushed_at":"2020-01-17T09:06:45Z","merges_url":"https:\/\/api.github.com\/repos\/4d-for-ios\/form-list-SquareProfile\/merges","open_issues_count":0,"watchers_count":0,"default_branch":"master","disabled":false,"clone_url":"https:\/\/github.com\/4d-for-ios\/form-list-SquareProfile.git","compare_url":"https:\/\/api.github.com\/repos\/4d-for-ios\/form-list-SquareProfile\/compare\/{base}...{head}","size":1998,"full_name":"4d-for-ios\/form-list-SquareProfile","assignees_url":"https:\/\/api.github.com\/repos\/4d-for-ios\/form-list-SquareProfile\/assignees{\/user}","forks_count":0,"license":{"key":"other","node_id":"MDc6TGljZW5zZTA=","url":null,"name":"Other","spdx_id":"NOASSERTION"},"archive_url":"https:\/\/api.github.com\/repos\/4d-for-ios\/form-list-SquareProfile\/{archive_format}{\/ref}","stargazers_count":0,"pulls_url":"https:\/\/api.github.com\/repos\/4d-for-ios\/form-list-SquareProfile\/pulls{\/number}","deployments_url":"https:\/\/api.github.com\/repos\/4d-for-ios\/form-list-SquareProfile\/deployments","owner":{"starred_url":"https:\/\/api.github.com\/users\/4d-for-ios\/starred{\/owner}{\/repo}","events_url":"https:\/\/api.github.com\/users\/4d-for-ios\/events{\/privacy}","avatar_url":"https:\/\/avatars.githubusercontent.com\/u\/57483781?v=4","node_id":"MDEyOk9yZ2FuaXphdGlvbjU3NDgzNzgx","organizations_url":"https:\/\/api.github.com\/users\/4d-for-ios\/orgs","id":57483781,"received_events_url":"https:\/\/api.github.com\/users\/4d-for-ios\/received_events","url":"https:\/\/api.github.com\/users\/4d-for-ios","login":"4d-for-ios","followers_url":"https:\/\/api.github.com\/users\/4d-for-ios\/followers","type":"Organization","subscriptions_url":"https:\/\/api.github.com\/users\/4d-for-ios\/subscriptions","html_url":"https:\/\/github.com\/4d-for-ios","following_url":"https:\/\/api.github.com\/users\/4d-for-ios\/following{\/other_user}","site_admin":false,"repos_url":"https:\/\/api.github.com\/users\/4d-for-ios\/repos","gists_url":"https:\/\/api.github.com\/users\/4d-for-ios\/gists{\/gist_id}","gravatar_id":""},"language":"Swift","milestones_url":"https:\/\/api.github.com\/repos\/4d-for-ios\/form-list-SquareProfile\/milestones{\/number}","contents_url":"https:\/\/api.github.com\/repos\/4d-for-ios\/form-list-SquareProfile\/contents\/{+path}","statuses_url":"https:\/\/api.github.com\/repos\/4d-for-ios\/form-list-SquareProfile\/statuses\/{sha}","commits_url":"https:\/\/api.github.com\/repos\/4d-for-ios\/form-list-SquareProfile\/commits{\/sha}","created_at":"2019-10-31T15:54:06Z","issues_url":"https:\/\/api.github.com\/repos\/4d-for-ios\/form-list-SquareProfile\/issues{\/number}","archived":false,"forks_url":"https:\/\/api.github.com\/repos\/4d-for-ios\/form-list-SquareProfile\/forks","labels_url":"https:\/\/api.github.com\/repos\/4d-for-ios\/form-list-SquareProfile\/labels{\/name}","organization":{"starred_url":"https:\/\/api.github.com\/users\/4d-for-ios\/starred{\/owner}{\/repo}","events_url":"https:\/\/api.github.com\/users\/4d-for-ios\/events{\/privacy}","avatar_url":"https:\/\/avatars.githubusercontent.com\/u\/57483781?v=4","node_id":"MDEyOk9yZ2FuaXphdGlvbjU3NDgzNzgx","organizations_url":"https:\/\/api.github.com\/users\/4d-for-ios\/orgs","id":57483781,"received_events_url":"https:\/\/api.github.com\/users\/4d-for-ios\/received_events","url":"https:\/\/api.github.com\/users\/4d-for-ios","login":"4d-for-ios","followers_url":"https:\/\/api.github.com\/users\/4d-for-ios\/followers","type":"Organization","subscriptions_url":"https:\/\/api.github.com\/users\/4d-for-ios\/subscriptions","html_url":"https:\/\/github.com\/4d-for-ios","following_url":"https:\/\/api.github.com\/users\/4d-for-ios\/following{\/other_user}","site_admin":false,"repos_url":"https:\/\/api.github.com\/users\/4d-for-ios\/repos","gists_url":"https:\/\/api.github.com\/users\/4d-for-ios\/gists{\/gist_id}","gravatar_id":""},"forks":0,"node_id":"MDEwOlJlcG9zaXRvcnkyMTg4MDM1MTI=","description":"4D for iOS List Form template"}