{"contents_url":"https:\/\/api.github.com\/repos\/4d-for-ios\/form-detail-SimpleList\/contents\/{+path}","notifications_url":"https:\/\/api.github.com\/repos\/4d-for-ios\/form-detail-SimpleList\/notifications{?since,all,participating}","contributors_url":"https:\/\/api.github.com\/repos\/4d-for-ios\/form-detail-SimpleList\/contributors","created_at":"2019-11-04T07:58:40Z","stargazers_url":"https:\/\/api.github.com\/repos\/4d-for-ios\/form-detail-SimpleList\/stargazers","commits_url":"https:\/\/api.github.com\/repos\/4d-for-ios\/form-detail-SimpleList\/commits{\/sha}","permissions":{"admin":false,"push":false,"pull":false},"archive_url":"https:\/\/api.github.com\/repos\/4d-for-ios\/form-detail-SimpleList\/{archive_format}{\/ref}","git_tags_url":"https:\/\/api.github.com\/repos\/4d-for-ios\/form-detail-SimpleList\/git\/tags{\/sha}","git_commits_url":"https:\/\/api.github.com\/repos\/4d-for-ios\/form-detail-SimpleList\/git\/commits{\/sha}","node_id":"MDEwOlJlcG9zaXRvcnkyMTk0NDcwNzI=","archived":false,"events_url":"https:\/\/api.github.com\/repos\/4d-for-ios\/form-detail-SimpleList\/events","visibility":"public","branches_url":"https:\/\/api.github.com\/repos\/4d-for-ios\/form-detail-SimpleList\/branches{\/branch}","languages_url":"https:\/\/api.github.com\/repos\/4d-for-ios\/form-detail-SimpleList\/languages","mirror_url":null,"collaborators_url":"https:\/\/api.github.com\/repos\/4d-for-ios\/form-detail-SimpleList\/collaborators{\/collaborator}","private":false,"downloads_url":"https:\/\/api.github.com\/repos\/4d-for-ios\/form-detail-SimpleList\/downloads","has_issues":true,"subscribers_count":2,"hooks_url":"https:\/\/api.github.com\/repos\/4d-for-ios\/form-detail-SimpleList\/hooks","tags_url":"https:\/\/api.github.com\/repos\/4d-for-ios\/form-detail-SimpleList\/tags","git_url":"git:\/\/github.com\/4d-for-ios\/form-detail-SimpleList.git","description":"4D for iOS Detail Form template","updated_at":"2020-01-17T09:09:58Z","network_count":0,"url":"https:\/\/api.github.com\/repos\/4d-for-ios\/form-detail-SimpleList","issue_events_url":"https:\/\/api.github.com\/repos\/4d-for-ios\/form-detail-SimpleList\/issues\/events{\/number}","homepage":"","has_downloads":true,"milestones_url":"https:\/\/api.github.com\/repos\/4d-for-ios\/form-detail-SimpleList\/milestones{\/number}","statuses_url":"https:\/\/api.github.com\/repos\/4d-for-ios\/form-detail-SimpleList\/statuses\/{sha}","keys_url":"https:\/\/api.github.com\/repos\/4d-for-ios\/form-detail-SimpleList\/keys{\/key_id}","has_projects":true,"open_issues_count":0,"forks":0,"labels_url":"https:\/\/api.github.com\/repos\/4d-for-ios\/form-detail-SimpleList\/labels{\/name}","issue_comment_url":"https:\/\/api.github.com\/repos\/4d-for-ios\/form-detail-SimpleList\/issues\/comments{\/number}","has_pages":false,"blobs_url":"https:\/\/api.github.com\/repos\/4d-for-ios\/form-detail-SimpleList\/git\/blobs{\/sha}","watchers_count":0,"comments_url":"https:\/\/api.github.com\/repos\/4d-for-ios\/form-detail-SimpleList\/comments{\/number}","svn_url":"https:\/\/github.com\/4d-for-ios\/form-detail-SimpleList","owner":{"login":"4d-for-ios","url":"https:\/\/api.github.com\/users\/4d-for-ios","events_url":"https:\/\/api.github.com\/users\/4d-for-ios\/events{\/privacy}","avatar_url":"https:\/\/avatars.githubusercontent.com\/u\/57483781?v=4","gravatar_id":"","starred_url":"https:\/\/api.github.com\/users\/4d-for-ios\/starred{\/owner}{\/repo}","node_id":"MDEyOk9yZ2FuaXphdGlvbjU3NDgzNzgx","repos_url":"https:\/\/api.github.com\/users\/4d-for-ios\/repos","id":57483781,"followers_url":"https:\/\/api.github.com\/users\/4d-for-ios\/followers","subscriptions_url":"https:\/\/api.github.com\/users\/4d-for-ios\/subscriptions","gists_url":"https:\/\/api.github.com\/users\/4d-for-ios\/gists{\/gist_id}","following_url":"https:\/\/api.github.com\/users\/4d-for-ios\/following{\/other_user}","received_events_url":"https:\/\/api.github.com\/users\/4d-for-ios\/received_events","site_admin":false,"organizations_url":"https:\/\/api.github.com\/users\/4d-for-ios\/orgs","html_url":"https:\/\/github.com\/4d-for-ios","type":"Organization"},"clone_url":"https:\/\/github.com\/4d-for-ios\/form-detail-SimpleList.git","temp_clone_token":"","forks_url":"https:\/\/api.github.com\/repos\/4d-for-ios\/form-detail-SimpleList\/forks","has_wiki":true,"html_url":"https:\/\/github.com\/4d-for-ios\/form-detail-SimpleList","forks_count":0,"ssh_url":"git@github.com:4d-for-ios\/form-detail-SimpleList.git","organization":{"login":"4d-for-ios","url":"https:\/\/api.github.com\/users\/4d-for-ios","events_url":"https:\/\/api.github.com\/users\/4d-for-ios\/events{\/privacy}","avatar_url":"https:\/\/avatars.githubusercontent.com\/u\/57483781?v=4","gravatar_id":"","starred_url":"https:\/\/api.github.com\/users\/4d-for-ios\/starred{\/owner}{\/repo}","node_id":"MDEyOk9yZ2FuaXphdGlvbjU3NDgzNzgx","repos_url":"https:\/\/api.github.com\/users\/4d-for-ios\/repos","id":57483781,"followers_url":"https:\/\/api.github.com\/users\/4d-for-ios\/followers","subscriptions_url":"https:\/\/api.github.com\/users\/4d-for-ios\/subscriptions","gists_url":"https:\/\/api.github.com\/users\/4d-for-ios\/gists{\/gist_id}","following_url":"https:\/\/api.github.com\/users\/4d-for-ios\/following{\/other_user}","received_events_url":"https:\/\/api.github.com\/users\/4d-for-ios\/received_events","site_admin":false,"organizations_url":"https:\/\/api.github.com\/users\/4d-for-ios\/orgs","html_url":"https:\/\/github.com\/4d-for-ios","type":"Organization"},"fork":false,"open_issues":0,"disabled":false,"assignees_url":"https:\/\/api.github.com\/repos\/4d-for-ios\/form-detail-SimpleList\/assignees{\/user}","stargazers_count":0,"name":"form-detail-SimpleList","releases_url":"https:\/\/api.github.com\/repos\/4d-for-ios\/form-detail-SimpleList\/releases{\/id}","pulls_url":"https:\/\/api.github.com\/repos\/4d-for-ios\/form-detail-SimpleList\/pulls{\/number}","trees_url":"https:\/\/api.github.com\/repos\/4d-for-ios\/form-detail-SimpleList\/git\/trees{\/sha}","issues_url":"https:\/\/api.github.com\/repos\/4d-for-ios\/form-detail-SimpleList\/issues{\/number}","license":{"key":"other","node_id":"MDc6TGljZW5zZTA=","url":null,"spdx_id":"NOASSERTION","name":"Other"},"subscription_url":"https:\/\/api.github.com\/repos\/4d-for-ios\/form-detail-SimpleList\/subscription","watchers":0,"size":514,"merges_url":"https:\/\/api.github.com\/repos\/4d-for-ios\/form-detail-SimpleList\/merges","deployments_url":"https:\/\/api.github.com\/repos\/4d-for-ios\/form-detail-SimpleList\/deployments","id":219447072,"pushed_at":"2020-01-17T09:09:56Z","release":{"upload_url":"https:\/\/uploads.github.com\/repos\/4d-for-ios\/form-detail-SimpleList\/releases\/21737599\/assets{?name,label}","tarball_url":"https:\/\/api.github.com\/repos\/4d-for-ios\/form-detail-SimpleList\/tarball\/0.0.1","created_at":"2019-11-25T09:48:12Z","name":null,"node_id":"MDc6UmVsZWFzZTIxNzM3NTk5","draft":false,"html_url":"https:\/\/github.com\/4d-for-ios\/form-detail-SimpleList\/releases\/tag\/0.0.1","id":21737599,"url":"https:\/\/api.github.com\/repos\/4d-for-ios\/form-detail-SimpleList\/releases\/21737599","assets":[{"browser_download_url":"https:\/\/github.com\/4d-for-ios\/form-detail-SimpleList\/releases\/download\/0.0.1\/form-detail-SimpleList.zip","label":"","download_count":28,"id":16387325,"state":"uploaded","created_at":"2019-11-25T16:16:58Z","node_id":"MDEyOlJlbGVhc2VBc3NldDE2Mzg3MzI1","url":"https:\/\/api.github.com\/repos\/4d-for-ios\/form-detail-SimpleList\/releases\/assets\/16387325","content_type":"application\/zip","updated_at":"2019-11-25T16:16:58Z","size":515920,"name":"form-detail-SimpleList.zip","uploader":{"repos_url":"https:\/\/api.github.com\/users\/github-actions%5Bbot%5D\/repos","following_url":"https:\/\/api.github.com\/users\/github-actions%5Bbot%5D\/following{\/other_user}","starred_url":"https:\/\/api.github.com\/users\/github-actions%5Bbot%5D\/starred{\/owner}{\/repo}","site_admin":false,"events_url":"https:\/\/api.github.com\/users\/github-actions%5Bbot%5D\/events{\/privacy}","followers_url":"https:\/\/api.github.com\/users\/github-actions%5Bbot%5D\/followers","type":"Bot","received_events_url":"https:\/\/api.github.com\/users\/github-actions%5Bbot%5D\/received_events","organizations_url":"https:\/\/api.github.com\/users\/github-actions%5Bbot%5D\/orgs","gravatar_id":"","gists_url":"https:\/\/api.github.com\/users\/github-actions%5Bbot%5D\/gists{\/gist_id}","url":"https:\/\/api.github.com\/users\/github-actions%5Bbot%5D","subscriptions_url":"https:\/\/api.github.com\/users\/github-actions%5Bbot%5D\/subscriptions","id":41898282,"avatar_url":"https:\/\/avatars.githubusercontent.com\/in\/15368?v=4","login":"github-actions[bot]","html_url":"https:\/\/github.com\/apps\/github-actions","node_id":"MDM6Qm90NDE4OTgyODI="}}],"assets_url":"https:\/\/api.github.com\/repos\/4d-for-ios\/form-detail-SimpleList\/releases\/21737599\/assets","target_commitish":"master","body":"🚀 Initial release","prerelease":false,"author":{"events_url":"https:\/\/api.github.com\/users\/phimage\/events{\/privacy}","node_id":"MDQ6VXNlcjg4NzU3Njg=","login":"phimage","received_events_url":"https:\/\/api.github.com\/users\/phimage\/received_events","following_url":"https:\/\/api.github.com\/users\/phimage\/following{\/other_user}","gravatar_id":"","avatar_url":"https:\/\/avatars.githubusercontent.com\/u\/8875768?v=4","url":"https:\/\/api.github.com\/users\/phimage","repos_url":"https:\/\/api.github.com\/users\/phimage\/repos","gists_url":"https:\/\/api.github.com\/users\/phimage\/gists{\/gist_id}","type":"User","site_admin":false,"starred_url":"https:\/\/api.github.com\/users\/phimage\/starred{\/owner}{\/repo}","followers_url":"https:\/\/api.github.com\/users\/phimage\/followers","organizations_url":"https:\/\/api.github.com\/users\/phimage\/orgs","html_url":"https:\/\/github.com\/phimage","subscriptions_url":"https:\/\/api.github.com\/users\/phimage\/subscriptions","id":8875768},"published_at":"2019-11-25T15:43:32Z","tag_name":"0.0.1","zipball_url":"https:\/\/api.github.com\/repos\/4d-for-ios\/form-detail-SimpleList\/zipball\/0.0.1"},"teams_url":"https:\/\/api.github.com\/repos\/4d-for-ios\/form-detail-SimpleList\/teams","full_name":"4d-for-ios\/form-detail-SimpleList","compare_url":"https:\/\/api.github.com\/repos\/4d-for-ios\/form-detail-SimpleList\/compare\/{base}...{head}","default_branch":"master","git_refs_url":"https:\/\/api.github.com\/repos\/4d-for-ios\/form-detail-SimpleList\/git\/refs{\/sha}","subscribers_url":"https:\/\/api.github.com\/repos\/4d-for-ios\/form-detail-SimpleList\/subscribers","language":"Swift"}